physics/__init__.py
physics/errors.py
physics/quantities.py
physics/utils.py
SciPhy-0.0.2.dist-info/LICENSE.txt
SciPhy-0.0.2.dist-info/METADATA
SciPhy-0.0.2.dist-info/WHEEL
SciPhy-0.0.2.dist-info/top_level.txt
SciPhy-0.0.2.dist-info/RECORD
